odoo/addons/purchase_tier_validation_forward/README.rst
odoo/addons/purchase_tier_validation_forward/__init__.py
odoo/addons/purchase_tier_validation_forward/__manifest__.py
odoo/addons/purchase_tier_validation_forward/i18n/purchase_tier_validation_forward.pot
odoo/addons/purchase_tier_validation_forward/i18n/zh_CN.po
odoo/addons/purchase_tier_validation_forward/readme/CONFIGURE.rst
odoo/addons/purchase_tier_validation_forward/readme/CONTRIBUTORS.rst
odoo/addons/purchase_tier_validation_forward/readme/DESCRIPTION.rst
odoo/addons/purchase_tier_validation_forward/readme/INSTALL.rst
odoo/addons/purchase_tier_validation_forward/static/description/icon.png
odoo/addons/purchase_tier_validation_forward/static/description/index.html
odoo/addons/purchase_tier_validation_forward/views/purchase_order_view.xml
odoo13_addon_purchase_tier_validation_forward-13.0.1.0.1.dist-info/METADATA
odoo13_addon_purchase_tier_validation_forward-13.0.1.0.1.dist-info/WHEEL
odoo13_addon_purchase_tier_validation_forward-13.0.1.0.1.dist-info/top_level.txt
odoo13_addon_purchase_tier_validation_forward-13.0.1.0.1.dist-info/RECORD
