Metadata-Version: 2.1
Name: odoo13-addon-purchase-tier-validation-forward
Version: 13.0.1.0.1
Summary: Purchase Tier Validation - Forward Option
Home-page: https://github.com/OCA/purchase-workflow
Author: Ecosoft,Odoo Community Association (OCA)
Author-email: support@odoo-community.org
License: AGPL-3
Platform: UNKNOWN
Classifier: Programming Language :: Python
Classifier: Framework :: Odoo
Classifier: Framework :: Odoo :: 13.0
Classifier: License :: OSI Approved :: GNU Affero General Public License v3
Classifier: Development Status :: 3 - Alpha
Requires-Python: >=3.5
Requires-Dist: odoo13-addon-base-tier-validation-forward
Requires-Dist: odoo13-addon-purchase-tier-validation
Requires-Dist: odoo (<13.1dev,>=13.0a)
